aergo/__init__.py
aergo/herapy/__init__.py
aergo/herapy/account.py
aergo/herapy/aergo.py
aergo/herapy/comm.py
aergo/herapy/constants.py
aergo/herapy/errors/InsufficientBalanceError.py
aergo/herapy/errors/__init__.py
aergo/herapy/errors/conversion_exception.py
aergo/herapy/errors/exception.py
aergo/herapy/errors/general_exception.py
aergo/herapy/grpc/__init__.py
aergo/herapy/grpc/account_pb2.py
aergo/herapy/grpc/account_pb2_grpc.py
aergo/herapy/grpc/blockchain_pb2.py
aergo/herapy/grpc/blockchain_pb2_grpc.py
aergo/herapy/grpc/metric_pb2.py
aergo/herapy/grpc/metric_pb2_grpc.py
aergo/herapy/grpc/node_pb2.py
aergo/herapy/grpc/node_pb2_grpc.py
aergo/herapy/grpc/p2p_pb2.py
aergo/herapy/grpc/p2p_pb2_grpc.py
aergo/herapy/grpc/pmap_pb2.py
aergo/herapy/grpc/pmap_pb2_grpc.py
aergo/herapy/grpc/polarrpc_pb2.py
aergo/herapy/grpc/polarrpc_pb2_grpc.py
aergo/herapy/grpc/raft_pb2.py
aergo/herapy/grpc/raft_pb2_grpc.py
aergo/herapy/grpc/rpc_pb2.py
aergo/herapy/grpc/rpc_pb2_grpc.py
aergo/herapy/obj/__init__.py
aergo/herapy/obj/abi.py
aergo/herapy/obj/address.py
aergo/herapy/obj/aer.py
aergo/herapy/obj/aergo_conf.py
aergo/herapy/obj/block.py
aergo/herapy/obj/block_hash.py
aergo/herapy/obj/block_meta_stream.py
aergo/herapy/obj/block_stream.py
aergo/herapy/obj/blockchain_info.py
aergo/herapy/obj/blockchain_status.py
aergo/herapy/obj/call_info.py
aergo/herapy/obj/chain_id.py
aergo/herapy/obj/change_conf_info.py
aergo/herapy/obj/consensus_info.py
aergo/herapy/obj/enterprise_config.py
aergo/herapy/obj/event.py
aergo/herapy/obj/event_stream.py
aergo/herapy/obj/name_info.py
aergo/herapy/obj/node_info.py
aergo/herapy/obj/peer.py
aergo/herapy/obj/private_key.py
aergo/herapy/obj/sc_state.py
aergo/herapy/obj/stream.py
aergo/herapy/obj/transaction.py
aergo/herapy/obj/tx_hash.py
aergo/herapy/obj/tx_result.py
aergo/herapy/obj/var_proof.py
aergo/herapy/status/__init__.py
aergo/herapy/status/commit_status.py
aergo/herapy/status/peer_status.py
aergo/herapy/status/tx_result_status.py
aergo_herapy-2.0.1.dist-info/AUTHORS.rst
aergo_herapy-2.0.1.dist-info/LICENSE
aergo_herapy-2.0.1.dist-info/METADATA
aergo_herapy-2.0.1.dist-info/WHEEL
aergo_herapy-2.0.1.dist-info/top_level.txt
aergo_herapy-2.0.1.dist-info/RECORD
