Metadata-Version: 2.1
Name: aergo-herapy
Version: 2.0.1
Summary: python SDK for AERGO
Home-page: https://github.com/aergoio/herapy
Author: aergo.io
Author-email: tech@aergo.io
License: MIT license
Keywords: herapy
Platform: UNKNOWN
Classifier: Development Status :: 5 - Production/Stable
Classifier: Intended Audience :: Developers
Classifier: License :: OSI Approved :: MIT License
Classifier: Natural Language :: English
Classifier: Programming Language :: Python :: 3.7
Requires-Dist: base58
Requires-Dist: ecdsa
Requires-Dist: googleapis-common-protos
Requires-Dist: protobuf
Requires-Dist: cryptography
Requires-Dist: toml
Requires-Dist: grpcio
